odoo/addons/easy_my_coop_website/README.rst
odoo/addons/easy_my_coop_website/__init__.py
odoo/addons/easy_my_coop_website/__manifest__.py
odoo/addons/easy_my_coop_website/controllers/__init__.py
odoo/addons/easy_my_coop_website/controllers/main.py
odoo/addons/easy_my_coop_website/data/website_cooperator_data.xml
odoo/addons/easy_my_coop_website/i18n/easy_my_coop_website.pot
odoo/addons/easy_my_coop_website/i18n/fr.po
odoo/addons/easy_my_coop_website/i18n/fr_BE.po
odoo/addons/easy_my_coop_website/models/__init__.py
odoo/addons/easy_my_coop_website/models/company.py
odoo/addons/easy_my_coop_website/readme/CONTRIBUTORS.rst
odoo/addons/easy_my_coop_website/readme/DESCRIPTION.rst
odoo/addons/easy_my_coop_website/static/description/index.html
odoo/addons/easy_my_coop_website/views/res_company_view.xml
odoo/addons/easy_my_coop_website/views/subscription_template.xml
odoo12_addon_easy_my_coop_website-12.0.1.1.1.dist-info/METADATA
odoo12_addon_easy_my_coop_website-12.0.1.1.1.dist-info/WHEEL
odoo12_addon_easy_my_coop_website-12.0.1.1.1.dist-info/top_level.txt
odoo12_addon_easy_my_coop_website-12.0.1.1.1.dist-info/RECORD
