Metadata-Version: 2.1
Name: odoo12-addon-easy-my-coop-website
Version: 12.0.1.1.1
Summary: This module adds the cooperator subscription form allowing to subscribe for shares online.
Home-page: https://coopiteasy.be
Author: Coop IT Easy SCRLfs
License: AGPL-3
Platform: UNKNOWN
Classifier: Programming Language :: Python
Classifier: Framework :: Odoo
Classifier: Framework :: Odoo :: 12.0
Classifier: License :: OSI Approved :: GNU Affero General Public License v3
Requires-Python: >=3.5
Requires-Dist: odoo12-addon-easy-my-coop
Requires-Dist: odoo12-addon-website-recaptcha-reloaded
Requires-Dist: odoo (<12.1dev,>=12.0a)
